{"type":"FeatureCollection","features":[{"type":"Feature","id":1,"geometry":{"type":"Point","coordinates":[-87.232641735069492,45.15986614223872]},"properties":{"OBJECTID":1,"site_id":"1","popup_desc":"Tennison Bay Campground","Image_url":"https://wisconsin.goingtocamp.com/","amenities":"188 sites, 97 electric, 2 ADA","site_type":"Summer, Winter"}},{"type":"Feature","id":2,"geometry":{"type":"Point","coordinates":[-87.239947071216861,45.134365967259299]},"properties":{"OBJECTID":2,"site_id":"2","popup_desc":"Weborg Point Campground","Image_url":"https://wisconsin.goingtocamp.com","amenities":"12 sites, 12 electric","site_type":"Summer"}},{"type":"Feature","id":3,"geometry":{"type":"Point","coordinates":[-87.224605932052199,45.172383709260927]},"properties":{"OBJECTID":3,"site_id":"3","popup_desc":"Welkers Point Campground","Image_url":"https://wisconsin.goingtocamp.com","amenities":"81 family sites, 0 electric","site_type":"Summer"}},{"type":"Feature","id":4,"geometry":{"type":"Point","coordinates":[-87.22456442539449,45.168541877234723]},"properties":{"OBJECTID":4,"site_id":"3","popup_desc":"North Nicolet Bay Campground","Image_url":"https://wisconsin.goingtocamp.com","amenities":"44 sites, 0 electric","site_type":"Summer"}},{"type":"Feature","id":5,"geometry":{"type":"Point","coordinates":[-87.219790321630526,45.163566611432962]},"properties":{"OBJECTID":5,"site_id":"4","popup_desc":"South Nicolet Bay Campground","Image_url":"https://wisconsin.goingtocamp.com","amenities":"143 sites, 54 electric, 2 ADA","site_type":"Summer"}}]}